autorubric/__init__.py
autorubric/dataset.py
autorubric/eval.py
autorubric/llm.py
autorubric/prompts.py
autorubric/rate_limit.py
autorubric/rubric.py
autorubric/types.py
autorubric/utils.py
autorubric/graders/__init__.py
autorubric/graders/base.py
autorubric/graders/criterion_grader.py
autorubric/metrics/__init__.py
autorubric/metrics/_compute.py
autorubric/metrics/_helpers.py
autorubric/metrics/_types.py
autorubric/metrics/distribution.py
autorubric-0.3.0.dist-info/METADATA
autorubric-0.3.0.dist-info/WHEEL
autorubric-0.3.0.dist-info/licenses/LICENSE
autorubric-0.3.0.dist-info/RECORD
