Metadata-Version: 2.4
Name: autorubric
Version: 0.3.0
Summary: A Python library encapsulating best practices for rubric-based evaluation of LLM/VLM outputs using LLM-as-a-judge.
Project-URL: Homepage, https://github.com/delip/autorubric
Project-URL: Repository, https://github.com/delip/autorubric
Project-URL: Issues, https://github.com/delip/autorubric/issues
Author: Delip Rao
License-Expression: MIT
License-File: LICENSE
Keywords: autorubric,eval,evaluation,grading,llm,llm as a judge,llm judge,rubrics
Classifier: Development Status :: 3 - Alpha
Classifier: Intended Audience :: Developers
Classifier: Intended Audience :: Education
Classifier: License :: OSI Approved :: MIT License
Classifier: Programming Language :: Python :: 3
Classifier: Programming Language :: Python :: 3.11
Classifier: Programming Language :: Python :: 3.12
Classifier: Programming Language :: Python :: 3.13
Classifier: Topic :: Education
Classifier: Topic :: Software Development :: Libraries :: Python Modules
Requires-Python: >=3.11
Requires-Dist: coolname>=2.0.0
Requires-Dist: diskcache>=5.6.0
Requires-Dist: litellm>=1.50.0
Requires-Dist: numpy>=1.24.0
Requires-Dist: pydantic>=2.0.0
Requires-Dist: python-dotenv>=1.0.0
Requires-Dist: pyyaml>=6.0.0
Requires-Dist: rich>=13.0.0
Requires-Dist: scikit-learn>=1.3.0
Requires-Dist: scipy>=1.10.0
Requires-Dist: tenacity>=8.2.0
